{"assets":{"F443A070570E84E4A145F1050C9A95C9":{"type":"texture","index":1,"assetRequest":{"type":"slide","state":"contents","slide":"none"},"url":{"native":"assets\/B33B744C-884B-449B-8C70-F6C936D0870F.pdf"},"width":731,"height":78},"7AAC0F4B7584D4356B06C17CD57555BD":{"type":"texture","index":2,"assetRequest":{"type":"slide","state":"contents","slide":"none"},"url":{"native":"assets\/B33B744C-884B-449B-8C70-F6C936D0870F.pdf"},"width":137,"height":23},"F33182DAF0802F86363CC427156904DD":{"type":"texture","index":4,"assetRequest":{"type":"slide","state":"contents","slide":"none"},"url":{"native":"assets\/B33B744C-884B-449B-8C70-F6C936D0870F.pdf"},"width":771,"height":85},"079F8AD6B4545016392B41106591B174":{"type":"texture","index":0,"assetRequest":{"type":"slide","state":"contents","slide":"none"},"url":{"native":"assets\/B33B744C-884B-449B-8C70-F6C936D0870F.pdf"},"width":960,"height":540},"3F92E9D33FC6814A8ECAE3254A8DC26C":{"type":"texture","index":7,"assetRequest":{"type":"slide","state":"contents","slide":"none"},"url":{"native":"assets\/B33B744C-884B-449B-8C70-F6C936D0870F.pdf"},"width":960,"height":540},"C464F2D59028BE3F1FC009DADE559130":{"type":"texture","index":5,"assetRequest":{"type":"slide","state":"contents","slide":"none"},"url":{"native":"assets\/B33B744C-884B-449B-8C70-F6C936D0870F.pdf"},"width":796,"height":86},"2E9FB1162F3DF28E3881A13DDAE96203":{"type":"texture","index":6,"assetRequest":{"type":"slide","state":"contents","slide":"none"},"url":{"native":"assets\/B33B744C-884B-449B-8C70-F6C936D0870F.pdf"},"width":504,"height":40},"5F50A526B1A711C07C54BC979DB6105C":{"type":"texture","index":8,"assetRequest":{"type":"slide","state":"contents","slide":"none"},"url":{"native":"assets\/B33B744C-884B-449B-8C70-F6C936D0870F.pdf"},"width":960,"height":540},"D94CCB6C708FE641EC745EEE0EC46C84":{"type":"texture","index":3,"assetRequest":{"type":"slide","state":"contents","slide":"none"},"url":{"native":"assets\/B33B744C-884B-449B-8C70-F6C936D0870F.pdf"},"width":787,"height":85}},"events":[{"effects":[{"beginTime":0,"baseLayer":{"animations":[],"initialState":{"affineTransform":[1,0,0,1,0,0],"masksToBounds":false,"rotation":0,"scale":1,"position":{"pointX":446.13999938964844,"pointY":178.16018676757812},"width":731,"sublayerTransform":[1,0,0,0,0,1,0,0,0,0,1,0,0,0,0,1],"contentsRect":{"y":0,"x":0,"width":1,"height":1},"opacity":1,"edgeAntialiasingMask":251658240,"height":78,"hidden":false,"anchorPoint":{"pointX":0.5,"pointY":0.5}},"objectID":"E7B7560B-CD61-4C89-AFD2-CEED0062D82E","layers":[{"animations":[],"initialState":{"affineTransform":[1,0,0,1,0,0],"masksToBounds":false,"rotation":0,"scale":1,"position":{"pointX":399.36000061035156,"pointY":130.83981323242188},"width":731,"sublayerTransform":[1,0,0,0,0,1,0,0,0,0,1,-0.00070015824933551967,0,0,0,1],"contentsRect":{"y":0,"x":0,"width":1,"height":1},"opacity":1,"edgeAntialiasingMask":251658240,"height":78,"hidden":false,"anchorPoint":{"pointX":0.54632011027407879,"pointY":1.6774335029797676}},"layers":[{"animations":[{"timeOffset":0,"beginTime":1e-100,"repeatCount":0,"animations":[{"timeOffset":0,"from":{"scalar":0},"beginTime":0,"repeatCount":0,"fillMode":"both","duration":1,"autoreverses":false,"timingFunction":"EaseInEaseOut","property":"opacity","to":{"scalar":1}},{"timeOffset":0,"from":{"scalar":false},"beginTime":0,"repeatCount":0,"fillMode":"forwards","property":"hidden","autoreverses":false,"duration":1,"to":{"scalar":false}}],"fillMode":"both","autoreverses":false,"duration":1}],"layers":[],"texturedRectangle":{"singleTextureOpacity":1,"textXHeight":0.20512820512820512,"textBaseline":0.97088380348988068,"isBackgroundTexture":true,"isVerticalText":false,"textColor":[0.38823530077934265,0.71764713525772095,0.35686266422271729,1],"textureType":6},"initialState":{"affineTransform":[1,0,0,1,0,0],"masksToBounds":false,"rotation":0,"scale":1,"position":{"pointX":368.86000061035156,"pointY":44.839813232421875},"width":731,"sublayerTransform":[1,0,0,0,0,1,0,0,0,0,1,0,0,0,0,1],"contentsRect":{"y":0,"x":0,"width":1,"height":1},"opacity":1,"edgeAntialiasingMask":0,"height":78,"hidden":true,"anchorPoint":{"pointX":0.5,"pointY":0.5}},"texture":"F443A070570E84E4A145F1050C9A95C9"}]}]},"effects":[],"duration":1,"type":"buildIn","name":"apple:dissolve character","objectID":"E7B7560B-CD61-4C89-AFD2-CEED0062D82E"}],"automaticPlay":false,"hyperlinks":[],"accessibility":[{"text":"Javascript operations","targetRectangle":{"y":75.680001735687256,"x":84.240006923675537,"width":500.88867140561342,"height":59}},{"text":"#SFNODE","targetRectangle":{"y":506.03670644760132,"x":812.03787851333618,"width":135.94970703125,"height":30}}],"baseLayer":{"animations":[],"initialState":{"affineTransform":[1,0,0,1,0,0],"masksToBounds":false,"rotation":0,"scale":1,"position":{"pointX":480,"pointY":270},"width":960,"sublayerTransform":[1,0,0,0,0,1,0,0,0,0,1,0,0,0,0,1],"contentsRect":{"y":0,"x":0,"width":1,"height":1},"opacity":1,"edgeAntialiasingMask":251658240,"height":540,"hidden":false,"anchorPoint":{"pointX":0.5,"pointY":0.5}},"layers":[{"animations":[],"initialState":{"affineTransform":[1,0,0,1,0,0],"masksToBounds":false,"rotation":0,"scale":1,"position":{"pointX":480,"pointY":270},"width":960,"sublayerTransform":[1,0,0,0,0,1,0,0,0,0,1,0,0,0,0,1],"contentsRect":{"y":0,"x":0,"width":1,"height":1},"opacity":1,"edgeAntialiasingMask":251658240,"height":540,"hidden":false,"anchorPoint":{"pointX":0.5,"pointY":0.5}},"layers":[{"animations":[],"initialState":{"affineTransform":[1,0,0,1,0,0],"masksToBounds":false,"rotation":0,"scale":1,"position":{"pointX":480,"pointY":270},"width":960,"sublayerTransform":[1,0,0,0,0,1,0,0,0,0,1,0,0,0,0,1],"contentsRect":{"y":0,"x":0,"width":1,"height":1},"opacity":1,"edgeAntialiasingMask":251658240,"height":540,"hidden":false,"anchorPoint":{"pointX":0.5,"pointY":0.5}},"layers":[{"animations":[],"layers":[],"texturedRectangle":{"isBackgroundTexture":true,"singleTextureOpacity":1,"textureType":1,"textBaseline":0,"textXHeight":0,"isVerticalText":false},"initialState":{"affineTransform":[1,0,0,1,0,0],"masksToBounds":false,"rotation":0,"scale":1,"position":{"pointX":480,"pointY":270},"width":960,"sublayerTransform":[1,0,0,0,0,1,0,0,0,0,1,0,0,0,0,1],"contentsRect":{"y":0,"x":0,"width":1,"height":1},"opacity":1,"edgeAntialiasingMask":0,"height":540,"hidden":false,"anchorPoint":{"pointX":0.5,"pointY":0.5}},"texture":"079F8AD6B4545016392B41106591B174"}]}]},{"animations":[],"initialState":{"affineTransform":[1,0,0,1,0,0],"masksToBounds":false,"rotation":0,"scale":1,"position":{"pointX":480,"pointY":270},"width":960,"sublayerTransform":[1,0,0,0,0,1,0,0,0,0,1,0,0,0,0,1],"contentsRect":{"y":0,"x":0,"width":1,"height":1},"opacity":1,"edgeAntialiasingMask":251658240,"height":540,"hidden":false,"anchorPoint":{"pointX":0.5,"pointY":0.5}},"layers":[{"animations":[],"initialState":{"affineTransform":[1,0,0,1,0,0],"masksToBounds":false,"rotation":0,"scale":1,"position":{"pointX":446.13999938964844,"pointY":178.16018676757812},"width":731,"sublayerTransform":[1,0,0,0,0,1,0,0,0,0,1,0,0,0,0,1],"contentsRect":{"y":0,"x":0,"width":1,"height":1},"opacity":1,"edgeAntialiasingMask":251658240,"height":78,"hidden":false,"anchorPoint":{"pointX":0.5,"pointY":0.5}},"objectID":"E7B7560B-CD61-4C89-AFD2-CEED0062D82E","layers":[{"animations":[],"layers":[],"texturedRectangle":{"singleTextureOpacity":1,"textXHeight":0.20512820512820512,"textBaseline":0.97088380348988068,"isBackgroundTexture":true,"isVerticalText":false,"textColor":[0.38823530077934265,0.71764713525772095,0.35686266422271729,1],"textureType":6},"initialState":{"affineTransform":[1,0,0,1,0,0],"masksToBounds":false,"rotation":0,"scale":1,"position":{"pointX":368.86000061035156,"pointY":44.839813232421875},"width":731,"sublayerTransform":[1,0,0,0,0,1,0,0,0,0,1,0,0,0,0,1],"contentsRect":{"y":0,"x":0,"width":1,"height":1},"opacity":1,"edgeAntialiasingMask":0,"height":78,"hidden":true,"anchorPoint":{"pointX":0.5,"pointY":0.5}},"texture":"F443A070570E84E4A145F1050C9A95C9"}]}]},{"animations":[],"initialState":{"affineTransform":[1,0,0,1,0,0],"masksToBounds":false,"rotation":0,"scale":1,"position":{"pointX":480,"pointY":270},"width":960,"sublayerTransform":[1,0,0,0,0,1,0,0,0,0,1,0,0,0,0,1],"contentsRect":{"y":0,"x":0,"width":1,"height":1},"opacity":1,"edgeAntialiasingMask":251658240,"height":540,"hidden":false,"anchorPoint":{"pointX":0.5,"pointY":0.5}},"layers":[{"animations":[],"initialState":{"affineTransform":[1,0,0,1,0,0],"masksToBounds":false,"rotation":0,"scale":1,"position":{"pointX":720.80072021484375,"pointY":513.93670654296875},"width":137,"sublayerTransform":[1,0,0,0,0,1,0,0,0,0,1,0,0,0,0,1],"contentsRect":{"y":0,"x":0,"width":1,"height":1},"opacity":1,"edgeAntialiasingMask":251658240,"height":23,"hidden":false,"anchorPoint":{"pointX":0.5,"pointY":0.5}},"layers":[{"animations":[],"layers":[],"texturedRectangle":{"singleTextureOpacity":1,"textXHeight":0.59602156929347827,"textBaseline":0.9038123047870138,"isBackgroundTexture":true,"isVerticalText":false,"textColor":[0.38823530077934265,0.71764713525772095,0.35686266422271729,1],"textureType":6},"initialState":{"affineTransform":[1,0,0,1,0,0],"masksToBounds":false,"rotation":0,"scale":1,"position":{"pointX":228.19927978515625,"pointY":19.06329345703125},"width":137,"sublayerTransform":[1,0,0,0,0,1,0,0,0,0,1,0,0,0,0,1],"contentsRect":{"y":0,"x":0,"width":1,"height":1},"opacity":1,"edgeAntialiasingMask":0,"height":23,"hidden":false,"anchorPoint":{"pointX":0.5,"pointY":0.5}},"texture":"7AAC0F4B7584D4356B06C17CD57555BD"}]}]},{"animations":[],"initialState":{"affineTransform":[1,0,0,1,0,0],"masksToBounds":false,"rotation":0,"scale":1,"position":{"pointX":480,"pointY":270},"width":960,"sublayerTransform":[1,0,0,0,0,1,0,0,0,0,1,0,0,0,0,1],"contentsRect":{"y":0,"x":0,"width":1,"height":1},"opacity":1,"edgeAntialiasingMask":251658240,"height":540,"hidden":false,"anchorPoint":{"pointX":0.5,"pointY":0.5}},"layers":[{"animations":[],"initialState":{"affineTransform":[1,0,0,1,0,0],"masksToBounds":false,"rotation":0,"scale":1,"position":{"pointX":474.13999938964844,"pointY":274.18991088867188},"width":787,"sublayerTransform":[1,0,0,0,0,1,0,0,0,0,1,0,0,0,0,1],"contentsRect":{"y":0,"x":0,"width":1,"height":1},"opacity":1,"edgeAntialiasingMask":251658240,"height":85,"hidden":false,"anchorPoint":{"pointX":0.5,"pointY":0.5}},"objectID":"2B50C4D3-6360-41FA-8440-50B175239820","layers":[{"animations":[],"layers":[],"texturedRectangle":{"singleTextureOpacity":1,"textXHeight":0.18823529411764706,"textBaseline":0.88539600933299345,"isBackgroundTexture":true,"isVerticalText":false,"textColor":[0.38823530077934265,0.71764713525772095,0.35686266422271729,1],"textureType":6},"initialState":{"affineTransform":[1,0,0,1,0,0],"masksToBounds":false,"rotation":0,"scale":1,"position":{"pointX":396.86000061035156,"pointY":48.810089111328125},"width":787,"sublayerTransform":[1,0,0,0,0,1,0,0,0,0,1,0,0,0,0,1],"contentsRect":{"y":0,"x":0,"width":1,"height":1},"opacity":1,"edgeAntialiasingMask":0,"height":85,"hidden":true,"anchorPoint":{"pointX":0.5,"pointY":0.5}},"texture":"D94CCB6C708FE641EC745EEE0EC46C84"}]}]},{"animations":[],"initialState":{"affineTransform":[1,0,0,1,0,0],"masksToBounds":false,"rotation":0,"scale":1,"position":{"pointX":480,"pointY":270},"width":960,"sublayerTransform":[1,0,0,0,0,1,0,0,0,0,1,0,0,0,0,1],"contentsRect":{"y":0,"x":0,"width":1,"height":1},"opacity":1,"edgeAntialiasingMask":251658240,"height":540,"hidden":false,"anchorPoint":{"pointX":0.5,"pointY":0.5}},"layers":[{"animations":[],"initialState":{"affineTransform":[1,0,0,1,0,0],"masksToBounds":false,"rotation":0,"scale":1,"position":{"pointX":466.13999938964844,"pointY":377.64059448242188},"width":771,"sublayerTransform":[1,0,0,0,0,1,0,0,0,0,1,0,0,0,0,1],"contentsRect":{"y":0,"x":0,"width":1,"height":1},"opacity":1,"edgeAntialiasingMask":251658240,"height":85,"hidden":false,"anchorPoint":{"pointX":0.5,"pointY":0.5}},"objectID":"3BA243F5-BC1B-483F-BCEF-51EEA0382C90","layers":[{"animations":[],"layers":[],"texturedRectangle":{"singleTextureOpacity":1,"textXHeight":0.18823529411764706,"textBaseline":0.89069816925946399,"isBackgroundTexture":true,"isVerticalText":false,"textColor":[0.38823530077934265,0.71764713525772095,0.35686266422271729,1],"textureType":6},"initialState":{"affineTransform":[1,0,0,1,0,0],"masksToBounds":false,"rotation":0,"scale":1,"position":{"pointX":388.86000061035156,"pointY":49.359405517578125},"width":771,"sublayerTransform":[1,0,0,0,0,1,0,0,0,0,1,0,0,0,0,1],"contentsRect":{"y":0,"x":0,"width":1,"height":1},"opacity":1,"edgeAntialiasingMask":0,"height":85,"hidden":true,"anchorPoint":{"pointX":0.5,"pointY":0.5}},"texture":"F33182DAF0802F86363CC427156904DD"}]}]},{"animations":[],"initialState":{"affineTransform":[1,0,0,1,0,0],"masksToBounds":false,"rotation":0,"scale":1,"position":{"pointX":480,"pointY":270},"width":960,"sublayerTransform":[1,0,0,0,0,1,0,0,0,0,1,0,0,0,0,1],"contentsRect":{"y":0,"x":0,"width":1,"height":1},"opacity":1,"edgeAntialiasingMask":251658240,"height":540,"hidden":false,"anchorPoint":{"pointX":0.5,"pointY":0.5}},"layers":[{"animations":[],"initialState":{"affineTransform":[1,0,0,1,0,0],"masksToBounds":false,"rotation":0,"scale":1,"position":{"pointX":478.63999938964844,"pointY":474.83148193359375},"width":796,"sublayerTransform":[1,0,0,0,0,1,0,0,0,0,1,0,0,0,0,1],"contentsRect":{"y":0,"x":0,"width":1,"height":1},"opacity":1,"edgeAntialiasingMask":251658240,"height":86,"hidden":false,"anchorPoint":{"pointX":0.5,"pointY":0.5}},"objectID":"4736A9F3-A4C1-4517-BA7C-0DD3768AF5F8","layers":[{"animations":[],"layers":[],"texturedRectangle":{"singleTextureOpacity":1,"textXHeight":0.18604651162790697,"textBaseline":0.88837478881658505,"isBackgroundTexture":true,"isVerticalText":false,"textColor":[0.38823530077934265,0.71764713525772095,0.35686266422271729,1],"textureType":6},"initialState":{"affineTransform":[1,0,0,1,0,0],"masksToBounds":false,"rotation":0,"scale":1,"position":{"pointX":401.36000061035156,"pointY":49.16851806640625},"width":796,"sublayerTransform":[1,0,0,0,0,1,0,0,0,0,1,0,0,0,0,1],"contentsRect":{"y":0,"x":0,"width":1,"height":1},"opacity":1,"edgeAntialiasingMask":0,"height":86,"hidden":true,"anchorPoint":{"pointX":0.5,"pointY":0.5}},"texture":"C464F2D59028BE3F1FC009DADE559130"}]}]},{"animations":[],"initialState":{"affineTransform":[1,0,0,1,0,0],"masksToBounds":false,"rotation":0,"scale":1,"position":{"pointX":480,"pointY":270},"width":960,"sublayerTransform":[1,0,0,0,0,1,0,0,0,0,1,0,0,0,0,1],"contentsRect":{"y":0,"x":0,"width":1,"height":1},"opacity":1,"edgeAntialiasingMask":251658240,"height":540,"hidden":false,"anchorPoint":{"pointX":0.5,"pointY":0.5}},"layers":[{"animations":[],"initialState":{"affineTransform":[1,0,0,1,0,0],"masksToBounds":false,"rotation":0,"scale":1,"position":{"pointX":332.64000701904297,"pointY":66.080001831054688},"width":504,"sublayerTransform":[1,0,0,0,0,1,0,0,0,0,1,0,0,0,0,1],"contentsRect":{"y":0,"x":0,"width":1,"height":1},"opacity":1,"edgeAntialiasingMask":251658240,"height":40,"hidden":false,"anchorPoint":{"pointX":0.5,"pointY":0.5}},"layers":[{"animations":[],"layers":[],"texturedRectangle":{"singleTextureOpacity":1,"textXHeight":0.56689453125,"textBaseline":0.90257133245468135,"isBackgroundTexture":true,"isVerticalText":false,"textColor":[0,0,0,1],"textureType":6},"initialState":{"affineTransform":[1,0,0,1,0,0],"masksToBounds":false,"rotation":0,"scale":1,"position":{"pointX":255.35999298095703,"pointY":59.919998168945312},"width":504,"sublayerTransform":[1,0,0,0,0,1,0,0,0,0,1,0,0,0,0,1],"contentsRect":{"y":0,"x":0,"width":1,"height":1},"opacity":1,"edgeAntialiasingMask":0,"height":40,"hidden":false,"anchorPoint":{"pointX":0.5,"pointY":0.5}},"texture":"2E9FB1162F3DF28E3881A13DDAE96203"}]}]}]}},{"effects":[{"beginTime":0,"baseLayer":{"animations":[],"initialState":{"affineTransform":[1,0,0,1,0,0],"masksToBounds":false,"rotation":0,"scale":1,"position":{"pointX":474.13999938964844,"pointY":274.18991088867188},"width":787,"sublayerTransform":[1,0,0,0,0,1,0,0,0,0,1,0,0,0,0,1],"contentsRect":{"y":0,"x":0,"width":1,"height":1},"opacity":1,"edgeAntialiasingMask":251658240,"height":85,"hidden":false,"anchorPoint":{"pointX":0.5,"pointY":0.5}},"objectID":"2B50C4D3-6360-41FA-8440-50B175239820","layers":[{"animations":[],"initialState":{"affineTransform":[1,0,0,1,0,0],"masksToBounds":false,"rotation":0,"scale":1,"position":{"pointX":399.36000061035156,"pointY":38.310089111328125},"width":787,"sublayerTransform":[1,0,0,0,0,1,0,0,0,0,1,-0.00070015824933551967,0,0,0,1],"contentsRect":{"y":0,"x":0,"width":1,"height":1},"opacity":1,"edgeAntialiasingMask":251658240,"height":85,"hidden":false,"anchorPoint":{"pointX":0.50744599823424597,"pointY":0.45070693072150736}},"layers":[{"animations":[{"timeOffset":0,"beginTime":1e-100,"repeatCount":0,"animations":[{"timeOffset":0,"from":{"scalar":0},"beginTime":0,"repeatCount":0,"fillMode":"both","duration":1,"autoreverses":false,"timingFunction":"EaseInEaseOut","property":"opacity","to":{"scalar":1}},{"timeOffset":0,"from":{"scalar":false},"beginTime":0,"repeatCount":0,"fillMode":"forwards","property":"hidden","autoreverses":false,"duration":1,"to":{"scalar":false}}],"fillMode":"both","autoreverses":false,"duration":1}],"layers":[],"texturedRectangle":{"singleTextureOpacity":1,"textXHeight":0.18823529411764706,"textBaseline":0.88539600933299345,"isBackgroundTexture":true,"isVerticalText":false,"textColor":[0.38823530077934265,0.71764713525772095,0.35686266422271729,1],"textureType":6},"initialState":{"affineTransform":[1,0,0,1,0,0],"masksToBounds":false,"rotation":0,"scale":1,"position":{"pointX":396.86000061035156,"pointY":48.810089111328125},"width":787,"sublayerTransform":[1,0,0,0,0,1,0,0,0,0,1,0,0,0,0,1],"contentsRect":{"y":0,"x":0,"width":1,"height":1},"opacity":1,"edgeAntialiasingMask":0,"height":85,"hidden":true,"anchorPoint":{"pointX":0.5,"pointY":0.5}},"texture":"D94CCB6C708FE641EC745EEE0EC46C84"}]}]},"effects":[],"duration":1,"type":"buildIn","name":"apple:dissolve character","objectID":"2B50C4D3-6360-41FA-8440-50B175239820"}],"automaticPlay":false,"hyperlinks":[],"accessibility":[{"text":"Javascript operations","targetRectangle":{"y":75.680001735687256,"x":84.240006923675537,"width":500.88867140561342,"height":59}},{"text":"The order that your code was written sometimes is different that will be executed","targetRectangle":{"y":142.76018667221069,"x":120.23999929428101,"width":701.6875,"height":86}},{"text":"#SFNODE","targetRectangle":{"y":506.03670644760132,"x":812.03787851333618,"width":135.94970703125,"height":30}}],"baseLayer":{"animations":[],"initialState":{"affineTransform":[1,0,0,1,0,0],"masksToBounds":false,"rotation":0,"scale":1,"position":{"pointX":480,"pointY":270},"width":960,"sublayerTransform":[1,0,0,0,0,1,0,0,0,0,1,0,0,0,0,1],"contentsRect":{"y":0,"x":0,"width":1,"height":1},"opacity":1,"edgeAntialiasingMask":251658240,"height":540,"hidden":false,"anchorPoint":{"pointX":0.5,"pointY":0.5}},"layers":[{"animations":[],"initialState":{"affineTransform":[1,0,0,1,0,0],"masksToBounds":false,"rotation":0,"scale":1,"position":{"pointX":480,"pointY":270},"width":960,"sublayerTransform":[1,0,0,0,0,1,0,0,0,0,1,0,0,0,0,1],"contentsRect":{"y":0,"x":0,"width":1,"height":1},"opacity":1,"edgeAntialiasingMask":251658240,"height":540,"hidden":false,"anchorPoint":{"pointX":0.5,"pointY":0.5}},"layers":[{"animations":[],"initialState":{"affineTransform":[1,0,0,1,0,0],"masksToBounds":false,"rotation":0,"scale":1,"position":{"pointX":480,"pointY":270},"width":960,"sublayerTransform":[1,0,0,0,0,1,0,0,0,0,1,0,0,0,0,1],"contentsRect":{"y":0,"x":0,"width":1,"height":1},"opacity":1,"edgeAntialiasingMask":251658240,"height":540,"hidden":false,"anchorPoint":{"pointX":0.5,"pointY":0.5}},"layers":[{"animations":[],"layers":[],"texturedRectangle":{"isBackgroundTexture":true,"singleTextureOpacity":1,"textureType":1,"textBaseline":0,"textXHeight":0,"isVerticalText":false},"initialState":{"affineTransform":[1,0,0,1,0,0],"masksToBounds":false,"rotation":0,"scale":1,"position":{"pointX":480,"pointY":270},"width":960,"sublayerTransform":[1,0,0,0,0,1,0,0,0,0,1,0,0,0,0,1],"contentsRect":{"y":0,"x":0,"width":1,"height":1},"opacity":1,"edgeAntialiasingMask":0,"height":540,"hidden":false,"anchorPoint":{"pointX":0.5,"pointY":0.5}},"texture":"079F8AD6B4545016392B41106591B174"}]}]},{"animations":[],"initialState":{"affineTransform":[1,0,0,1,0,0],"masksToBounds":false,"rotation":0,"scale":1,"position":{"pointX":480,"pointY":270},"width":960,"sublayerTransform":[1,0,0,0,0,1,0,0,0,0,1,0,0,0,0,1],"contentsRect":{"y":0,"x":0,"width":1,"height":1},"opacity":1,"edgeAntialiasingMask":251658240,"height":540,"hidden":false,"anchorPoint":{"pointX":0.5,"pointY":0.5}},"layers":[{"animations":[],"initialState":{"affineTransform":[1,0,0,1,0,0],"masksToBounds":false,"rotation":0,"scale":1,"position":{"pointX":446.13999938964844,"pointY":178.16018676757812},"width":731,"sublayerTransform":[1,0,0,0,0,1,0,0,0,0,1,0,0,0,0,1],"contentsRect":{"y":0,"x":0,"width":1,"height":1},"opacity":1,"edgeAntialiasingMask":251658240,"height":78,"hidden":false,"anchorPoint":{"pointX":0.5,"pointY":0.5}},"objectID":"E7B7560B-CD61-4C89-AFD2-CEED0062D82E","layers":[{"animations":[],"layers":[],"texturedRectangle":{"singleTextureOpacity":1,"textXHeight":0.20512820512820512,"textBaseline":0.97088380348988068,"isBackgroundTexture":true,"isVerticalText":false,"textColor":[0.38823530077934265,0.71764713525772095,0.35686266422271729,1],"textureType":6},"initialState":{"affineTransform":[1,0,0,1,0,0],"masksToBounds":false,"rotation":0,"scale":1,"position":{"pointX":368.86000061035156,"pointY":44.839813232421875},"width":731,"sublayerTransform":[1,0,0,0,0,1,0,0,0,0,1,0,0,0,0,1],"contentsRect":{"y":0,"x":0,"width":1,"height":1},"opacity":1,"edgeAntialiasingMask":0,"height":78,"hidden":false,"anchorPoint":{"pointX":0.5,"pointY":0.5}},"texture":"F443A070570E84E4A145F1050C9A95C9"}]}]},{"animations":[],"initialState":{"affineTransform":[1,0,0,1,0,0],"masksToBounds":false,"rotation":0,"scale":1,"position":{"pointX":480,"pointY":270},"width":960,"sublayerTransform":[1,0,0,0,0,1,0,0,0,0,1,0,0,0,0,1],"contentsRect":{"y":0,"x":0,"width":1,"height":1},"opacity":1,"edgeAntialiasingMask":251658240,"height":540,"hidden":false,"anchorPoint":{"pointX":0.5,"pointY":0.5}},"layers":[{"animations":[],"initialState":{"affineTransform":[1,0,0,1,0,0],"masksToBounds":false,"rotation":0,"scale":1,"position":{"pointX":720.80072021484375,"pointY":513.93670654296875},"width":137,"sublayerTransform":[1,0,0,0,0,1,0,0,0,0,1,0,0,0,0,1],"contentsRect":{"y":0,"x":0,"width":1,"height":1},"opacity":1,"edgeAntialiasingMask":251658240,"height":23,"hidden":false,"anchorPoint":{"pointX":0.5,"pointY":0.5}},"layers":[{"animations":[],"layers":[],"texturedRectangle":{"singleTextureOpacity":1,"textXHeight":0.59602156929347827,"textBaseline":0.9038123047870138,"isBackgroundTexture":true,"isVerticalText":false,"textColor":[0.38823530077934265,0.71764713525772095,0.35686266422271729,1],"textureType":6},"initialState":{"affineTransform":[1,0,0,1,0,0],"masksToBounds":false,"rotation":0,"scale":1,"position":{"pointX":228.19927978515625,"pointY":19.06329345703125},"width":137,"sublayerTransform":[1,0,0,0,0,1,0,0,0,0,1,0,0,0,0,1],"contentsRect":{"y":0,"x":0,"width":1,"height":1},"opacity":1,"edgeAntialiasingMask":0,"height":23,"hidden":false,"anchorPoint":{"pointX":0.5,"pointY":0.5}},"texture":"7AAC0F4B7584D4356B06C17CD57555BD"}]}]},{"animations":[],"initialState":{"affineTransform":[1,0,0,1,0,0],"masksToBounds":false,"rotation":0,"scale":1,"position":{"pointX":480,"pointY":270},"width":960,"sublayerTransform":[1,0,0,0,0,1,0,0,0,0,1,0,0,0,0,1],"contentsRect":{"y":0,"x":0,"width":1,"height":1},"opacity":1,"edgeAntialiasingMask":251658240,"height":540,"hidden":false,"anchorPoint":{"pointX":0.5,"pointY":0.5}},"layers":[{"animations":[],"initialState":{"affineTransform":[1,0,0,1,0,0],"masksToBounds":false,"rotation":0,"scale":1,"position":{"pointX":474.13999938964844,"pointY":274.18991088867188},"width":787,"sublayerTransform":[1,0,0,0,0,1,0,0,0,0,1,0,0,0,0,1],"contentsRect":{"y":0,"x":0,"width":1,"height":1},"opacity":1,"edgeAntialiasingMask":251658240,"height":85,"hidden":false,"anchorPoint":{"pointX":0.5,"pointY":0.5}},"objectID":"2B50C4D3-6360-41FA-8440-50B175239820","layers":[{"animations":[],"layers":[],"texturedRectangle":{"singleTextureOpacity":1,"textXHeight":0.18823529411764706,"textBaseline":0.88539600933299345,"isBackgroundTexture":true,"isVerticalText":false,"textColor":[0.38823530077934265,0.71764713525772095,0.35686266422271729,1],"textureType":6},"initialState":{"affineTransform":[1,0,0,1,0,0],"masksToBounds":false,"rotation":0,"scale":1,"position":{"pointX":396.86000061035156,"pointY":48.810089111328125},"width":787,"sublayerTransform":[1,0,0,0,0,1,0,0,0,0,1,0,0,0,0,1],"contentsRect":{"y":0,"x":0,"width":1,"height":1},"opacity":1,"edgeAntialiasingMask":0,"height":85,"hidden":true,"anchorPoint":{"pointX":0.5,"pointY":0.5}},"texture":"D94CCB6C708FE641EC745EEE0EC46C84"}]}]},{"animations":[],"initialState":{"affineTransform":[1,0,0,1,0,0],"masksToBounds":false,"rotation":0,"scale":1,"position":{"pointX":480,"pointY":270},"width":960,"sublayerTransform":[1,0,0,0,0,1,0,0,0,0,1,0,0,0,0,1],"contentsRect":{"y":0,"x":0,"width":1,"height":1},"opacity":1,"edgeAntialiasingMask":251658240,"height":540,"hidden":false,"anchorPoint":{"pointX":0.5,"pointY":0.5}},"layers":[{"animations":[],"initialState":{"affineTransform":[1,0,0,1,0,0],"masksToBounds":false,"rotation":0,"scale":1,"position":{"pointX":466.13999938964844,"pointY":377.64059448242188},"width":771,"sublayerTransform":[1,0,0,0,0,1,0,0,0,0,1,0,0,0,0,1],"contentsRect":{"y":0,"x":0,"width":1,"height":1},"opacity":1,"edgeAntialiasingMask":251658240,"height":85,"hidden":false,"anchorPoint":{"pointX":0.5,"pointY":0.5}},"objectID":"3BA243F5-BC1B-483F-BCEF-51EEA0382C90","layers":[{"animations":[],"layers":[],"texturedRectangle":{"singleTextureOpacity":1,"textXHeight":0.18823529411764706,"textBaseline":0.89069816925946399,"isBackgroundTexture":true,"isVerticalText":false,"textColor":[0.38823530077934265,0.71764713525772095,0.35686266422271729,1],"textureType":6},"initialState":{"affineTransform":[1,0,0,1,0,0],"masksToBounds":false,"rotation":0,"scale":1,"position":{"pointX":388.86000061035156,"pointY":49.359405517578125},"width":771,"sublayerTransform":[1,0,0,0,0,1,0,0,0,0,1,0,0,0,0,1],"contentsRect":{"y":0,"x":0,"width":1,"height":1},"opacity":1,"edgeAntialiasingMask":0,"height":85,"hidden":true,"anchorPoint":{"pointX":0.5,"pointY":0.5}},"texture":"F33182DAF0802F86363CC427156904DD"}]}]},{"animations":[],"initialState":{"affineTransform":[1,0,0,1,0,0],"masksToBounds":false,"rotation":0,"scale":1,"position":{"pointX":480,"pointY":270},"width":960,"sublayerTransform":[1,0,0,0,0,1,0,0,0,0,1,0,0,0,0,1],"contentsRect":{"y":0,"x":0,"width":1,"height":1},"opacity":1,"edgeAntialiasingMask":251658240,"height":540,"hidden":false,"anchorPoint":{"pointX":0.5,"pointY":0.5}},"layers":[{"animations":[],"initialState":{"affineTransform":[1,0,0,1,0,0],"masksToBounds":false,"rotation":0,"scale":1,"position":{"pointX":478.63999938964844,"pointY":474.83148193359375},"width":796,"sublayerTransform":[1,0,0,0,0,1,0,0,0,0,1,0,0,0,0,1],"contentsRect":{"y":0,"x":0,"width":1,"height":1},"opacity":1,"edgeAntialiasingMask":251658240,"height":86,"hidden":false,"anchorPoint":{"pointX":0.5,"pointY":0.5}},"objectID":"4736A9F3-A4C1-4517-BA7C-0DD3768AF5F8","layers":[{"animations":[],"layers":[],"texturedRectangle":{"singleTextureOpacity":1,"textXHeight":0.18604651162790697,"textBaseline":0.88837478881658505,"isBackgroundTexture":true,"isVerticalText":false,"textColor":[0.38823530077934265,0.71764713525772095,0.35686266422271729,1],"textureType":6},"initialState":{"affineTransform":[1,0,0,1,0,0],"masksToBounds":false,"rotation":0,"scale":1,"position":{"pointX":401.36000061035156,"pointY":49.16851806640625},"width":796,"sublayerTransform":[1,0,0,0,0,1,0,0,0,0,1,0,0,0,0,1],"contentsRect":{"y":0,"x":0,"width":1,"height":1},"opacity":1,"edgeAntialiasingMask":0,"height":86,"hidden":true,"anchorPoint":{"pointX":0.5,"pointY":0.5}},"texture":"C464F2D59028BE3F1FC009DADE559130"}]}]},{"animations":[],"initialState":{"affineTransform":[1,0,0,1,0,0],"masksToBounds":false,"rotation":0,"scale":1,"position":{"pointX":480,"pointY":270},"width":960,"sublayerTransform":[1,0,0,0,0,1,0,0,0,0,1,0,0,0,0,1],"contentsRect":{"y":0,"x":0,"width":1,"height":1},"opacity":1,"edgeAntialiasingMask":251658240,"height":540,"hidden":false,"anchorPoint":{"pointX":0.5,"pointY":0.5}},"layers":[{"animations":[],"initialState":{"affineTransform":[1,0,0,1,0,0],"masksToBounds":false,"rotation":0,"scale":1,"position":{"pointX":332.64000701904297,"pointY":66.080001831054688},"width":504,"sublayerTransform":[1,0,0,0,0,1,0,0,0,0,1,0,0,0,0,1],"contentsRect":{"y":0,"x":0,"width":1,"height":1},"opacity":1,"edgeAntialiasingMask":251658240,"height":40,"hidden":false,"anchorPoint":{"pointX":0.5,"pointY":0.5}},"layers":[{"animations":[],"layers":[],"texturedRectangle":{"singleTextureOpacity":1,"textXHeight":0.56689453125,"textBaseline":0.90257133245468135,"isBackgroundTexture":true,"isVerticalText":false,"textColor":[0,0,0,1],"textureType":6},"initialState":{"affineTransform":[1,0,0,1,0,0],"masksToBounds":false,"rotation":0,"scale":1,"position":{"pointX":255.35999298095703,"pointY":59.919998168945312},"width":504,"sublayerTransform":[1,0,0,0,0,1,0,0,0,0,1,0,0,0,0,1],"contentsRect":{"y":0,"x":0,"width":1,"height":1},"opacity":1,"edgeAntialiasingMask":0,"height":40,"hidden":false,"anchorPoint":{"pointX":0.5,"pointY":0.5}},"texture":"2E9FB1162F3DF28E3881A13DDAE96203"}]}]}]}},{"effects":[{"beginTime":0,"baseLayer":{"animations":[],"initialState":{"affineTransform":[1,0,0,1,0,0],"masksToBounds":false,"rotation":0,"scale":1,"position":{"pointX":466.13999938964844,"pointY":377.64059448242188},"width":771,"sublayerTransform":[1,0,0,0,0,1,0,0,0,0,1,0,0,0,0,1],"contentsRect":{"y":0,"x":0,"width":1,"height":1},"opacity":1,"edgeAntialiasingMask":251658240,"height":85,"hidden":false,"anchorPoint":{"pointX":0.5,"pointY":0.5}},"objectID":"3BA243F5-BC1B-483F-BCEF-51EEA0382C90","layers":[{"animations":[],"initialState":{"affineTransform":[1,0,0,1,0,0],"masksToBounds":false,"rotation":0,"scale":1,"position":{"pointX":399.36000061035156,"pointY":-65.140594482421875},"width":771,"sublayerTransform":[1,0,0,0,0,1,0,0,0,0,1,-0.00070015824933551967,0,0,0,1],"contentsRect":{"y":0,"x":0,"width":1,"height":1},"opacity":1,"edgeAntialiasingMask":251658240,"height":85,"hidden":false,"anchorPoint":{"pointX":0.51797665448813435,"pointY":-0.76635993508731615}},"layers":[{"animations":[{"timeOffset":0,"beginTime":1e-100,"repeatCount":0,"animations":[{"timeOffset":0,"from":{"scalar":0},"beginTime":0,"repeatCount":0,"fillMode":"both","duration":1,"autoreverses":false,"timingFunction":"EaseInEaseOut","property":"opacity","to":{"scalar":1}},{"timeOffset":0,"from":{"scalar":false},"beginTime":0,"repeatCount":0,"fillMode":"forwards","property":"hidden","autoreverses":false,"duration":1,"to":{"scalar":false}}],"fillMode":"both","autoreverses":false,"duration":1}],"layers":[],"texturedRectangle":{"singleTextureOpacity":1,"textXHeight":0.18823529411764706,"textBaseline":0.89069816925946399,"isBackgroundTexture":true,"isVerticalText":false,"textColor":[0.38823530077934265,0.71764713525772095,0.35686266422271729,1],"textureType":6},"initialState":{"affineTransform":[1,0,0,1,0,0],"masksToBounds":false,"rotation":0,"scale":1,"position":{"pointX":388.86000061035156,"pointY":49.359405517578125},"width":771,"sublayerTransform":[1,0,0,0,0,1,0,0,0,0,1,0,0,0,0,1],"contentsRect":{"y":0,"x":0,"width":1,"height":1},"opacity":1,"edgeAntialiasingMask":0,"height":85,"hidden":true,"anchorPoint":{"pointX":0.5,"pointY":0.5}},"texture":"F33182DAF0802F86363CC427156904DD"}]}]},"effects":[],"duration":1,"type":"buildIn","name":"apple:dissolve character","objectID":"3BA243F5-BC1B-483F-BCEF-51EEA0382C90"}],"automaticPlay":false,"hyperlinks":[],"accessibility":[{"text":"Javascript operations","targetRectangle":{"y":75.680001735687256,"x":84.240006923675537,"width":500.88867140561342,"height":59}},{"text":"All outside operations (Database connections, WebSite requests, etc) needs to be synchronised with callbacks","targetRectangle":{"y":235.28991079330444,"x":120.23999929428101,"width":757.1875,"height":86}},{"text":"The order that your code was written sometimes is different that will be executed","targetRectangle":{"y":142.76018667221069,"x":120.23999929428101,"width":701.6875,"height":86}},{"text":"#SFNODE","targetRectangle":{"y":506.03670644760132,"x":812.03787851333618,"width":135.94970703125,"height":30}}],"baseLayer":{"animations":[],"initialState":{"affineTransform":[1,0,0,1,0,0],"masksToBounds":false,"rotation":0,"scale":1,"position":{"pointX":480,"pointY":270},"width":960,"sublayerTransform":[1,0,0,0,0,1,0,0,0,0,1,0,0,0,0,1],"contentsRect":{"y":0,"x":0,"width":1,"height":1},"opacity":1,"edgeAntialiasingMask":251658240,"height":540,"hidden":false,"anchorPoint":{"pointX":0.5,"pointY":0.5}},"layers":[{"animations":[],"initialState":{"affineTransform":[1,0,0,1,0,0],"masksToBounds":false,"rotation":0,"scale":1,"position":{"pointX":480,"pointY":270},"width":960,"sublayerTransform":[1,0,0,0,0,1,0,0,0,0,1,0,0,0,0,1],"contentsRect":{"y":0,"x":0,"width":1,"height":1},"opacity":1,"edgeAntialiasingMask":251658240,"height":540,"hidden":false,"anchorPoint":{"pointX":0.5,"pointY":0.5}},"layers":[{"animations":[],"initialState":{"affineTransform":[1,0,0,1,0,0],"masksToBounds":false,"rotation":0,"scale":1,"position":{"pointX":480,"pointY":270},"width":960,"sublayerTransform":[1,0,0,0,0,1,0,0,0,0,1,0,0,0,0,1],"contentsRect":{"y":0,"x":0,"width":1,"height":1},"opacity":1,"edgeAntialiasingMask":251658240,"height":540,"hidden":false,"anchorPoint":{"pointX":0.5,"pointY":0.5}},"layers":[{"animations":[],"layers":[],"texturedRectangle":{"isBackgroundTexture":true,"singleTextureOpacity":1,"textureType":1,"textBaseline":0,"textXHeight":0,"isVerticalText":false},"initialState":{"affineTransform":[1,0,0,1,0,0],"masksToBounds":false,"rotation":0,"scale":1,"position":{"pointX":480,"pointY":270},"width":960,"sublayerTransform":[1,0,0,0,0,1,0,0,0,0,1,0,0,0,0,1],"contentsRect":{"y":0,"x":0,"width":1,"height":1},"opacity":1,"edgeAntialiasingMask":0,"height":540,"hidden":false,"anchorPoint":{"pointX":0.5,"pointY":0.5}},"texture":"079F8AD6B4545016392B41106591B174"}]}]},{"animations":[],"initialState":{"affineTransform":[1,0,0,1,0,0],"masksToBounds":false,"rotation":0,"scale":1,"position":{"pointX":480,"pointY":270},"width":960,"sublayerTransform":[1,0,0,0,0,1,0,0,0,0,1,0,0,0,0,1],"contentsRect":{"y":0,"x":0,"width":1,"height":1},"opacity":1,"edgeAntialiasingMask":251658240,"height":540,"hidden":false,"anchorPoint":{"pointX":0.5,"pointY":0.5}},"layers":[{"animations":[],"initialState":{"affineTransform":[1,0,0,1,0,0],"masksToBounds":false,"rotation":0,"scale":1,"position":{"pointX":446.13999938964844,"pointY":178.16018676757812},"width":731,"sublayerTransform":[1,0,0,0,0,1,0,0,0,0,1,0,0,0,0,1],"contentsRect":{"y":0,"x":0,"width":1,"height":1},"opacity":1,"edgeAntialiasingMask":251658240,"height":78,"hidden":false,"anchorPoint":{"pointX":0.5,"pointY":0.5}},"objectID":"E7B7560B-CD61-4C89-AFD2-CEED0062D82E","layers":[{"animations":[],"layers":[],"texturedRectangle":{"singleTextureOpacity":1,"textXHeight":0.20512820512820512,"textBaseline":0.97088380348988068,"isBackgroundTexture":true,"isVerticalText":false,"textColor":[0.38823530077934265,0.71764713525772095,0.35686266422271729,1],"textureType":6},"initialState":{"affineTransform":[1,0,0,1,0,0],"masksToBounds":false,"rotation":0,"scale":1,"position":{"pointX":368.86000061035156,"pointY":44.839813232421875},"width":731,"sublayerTransform":[1,0,0,0,0,1,0,0,0,0,1,0,0,0,0,1],"contentsRect":{"y":0,"x":0,"width":1,"height":1},"opacity":1,"edgeAntialiasingMask":0,"height":78,"hidden":false,"anchorPoint":{"pointX":0.5,"pointY":0.5}},"texture":"F443A070570E84E4A145F1050C9A95C9"}]}]},{"animations":[],"initialState":{"affineTransform":[1,0,0,1,0,0],"masksToBounds":false,"rotation":0,"scale":1,"position":{"pointX":480,"pointY":270},"width":960,"sublayerTransform":[1,0,0,0,0,1,0,0,0,0,1,0,0,0,0,1],"contentsRect":{"y":0,"x":0,"width":1,"height":1},"opacity":1,"edgeAntialiasingMask":251658240,"height":540,"hidden":false,"anchorPoint":{"pointX":0.5,"pointY":0.5}},"layers":[{"animations":[],"initialState":{"affineTransform":[1,0,0,1,0,0],"masksToBounds":false,"rotation":0,"scale":1,"position":{"pointX":720.80072021484375,"pointY":513.93670654296875},"width":137,"sublayerTransform":[1,0,0,0,0,1,0,0,0,0,1,0,0,0,0,1],"contentsRect":{"y":0,"x":0,"width":1,"height":1},"opacity":1,"edgeAntialiasingMask":251658240,"height":23,"hidden":false,"anchorPoint":{"pointX":0.5,"pointY":0.5}},"layers":[{"animations":[],"layers":[],"texturedRectangle":{"singleTextureOpacity":1,"textXHeight":0.59602156929347827,"textBaseline":0.9038123047870138,"isBackgroundTexture":true,"isVerticalText":false,"textColor":[0.38823530077934265,0.71764713525772095,0.35686266422271729,1],"textureType":6},"initialState":{"affineTransform":[1,0,0,1,0,0],"masksToBounds":false,"rotation":0,"scale":1,"position":{"pointX":228.19927978515625,"pointY":19.06329345703125},"width":137,"sublayerTransform":[1,0,0,0,0,1,0,0,0,0,1,0,0,0,0,1],"contentsRect":{"y":0,"x":0,"width":1,"height":1},"opacity":1,"edgeAntialiasingMask":0,"height":23,"hidden":false,"anchorPoint":{"pointX":0.5,"pointY":0.5}},"texture":"7AAC0F4B7584D4356B06C17CD57555BD"}]}]},{"animations":[],"initialState":{"affineTransform":[1,0,0,1,0,0],"masksToBounds":false,"rotation":0,"scale":1,"position":{"pointX":480,"pointY":270},"width":960,"sublayerTransform":[1,0,0,0,0,1,0,0,0,0,1,0,0,0,0,1],"contentsRect":{"y":0,"x":0,"width":1,"height":1},"opacity":1,"edgeAntialiasingMask":251658240,"height":540,"hidden":false,"anchorPoint":{"pointX":0.5,"pointY":0.5}},"layers":[{"animations":[],"initialState":{"affineTransform":[1,0,0,1,0,0],"masksToBounds":false,"rotation":0,"scale":1,"position":{"pointX":474.13999938964844,"pointY":274.18991088867188},"width":787,"sublayerTransform":[1,0,0,0,0,1,0,0,0,0,1,0,0,0,0,1],"contentsRect":{"y":0,"x":0,"width":1,"height":1},"opacity":1,"edgeAntialiasingMask":251658240,"height":85,"hidden":false,"anchorPoint":{"pointX":0.5,"pointY":0.5}},"objectID":"2B50C4D3-6360-41FA-8440-50B175239820","layers":[{"animations":[],"layers":[],"texturedRectangle":{"singleTextureOpacity":1,"textXHeight":0.18823529411764706,"textBaseline":0.88539600933299345,"isBackgroundTexture":true,"isVerticalText":false,"textColor":[0.38823530077934265,0.71764713525772095,0.35686266422271729,1],"textureType":6},"initialState":{"affineTransform":[1,0,0,1,0,0],"masksToBounds":false,"rotation":0,"scale":1,"position":{"pointX":396.86000061035156,"pointY":48.810089111328125},"width":787,"sublayerTransform":[1,0,0,0,0,1,0,0,0,0,1,0,0,0,0,1],"contentsRect":{"y":0,"x":0,"width":1,"height":1},"opacity":1,"edgeAntialiasingMask":0,"height":85,"hidden":false,"anchorPoint":{"pointX":0.5,"pointY":0.5}},"texture":"D94CCB6C708FE641EC745EEE0EC46C84"}]}]},{"animations":[],"initialState":{"affineTransform":[1,0,0,1,0,0],"masksToBounds":false,"rotation":0,"scale":1,"position":{"pointX":480,"pointY":270},"width":960,"sublayerTransform":[1,0,0,0,0,1,0,0,0,0,1,0,0,0,0,1],"contentsRect":{"y":0,"x":0,"width":1,"height":1},"opacity":1,"edgeAntialiasingMask":251658240,"height":540,"hidden":false,"anchorPoint":{"pointX":0.5,"pointY":0.5}},"layers":[{"animations":[],"initialState":{"affineTransform":[1,0,0,1,0,0],"masksToBounds":false,"rotation":0,"scale":1,"position":{"pointX":466.13999938964844,"pointY":377.64059448242188},"width":771,"sublayerTransform":[1,0,0,0,0,1,0,0,0,0,1,0,0,0,0,1],"contentsRect":{"y":0,"x":0,"width":1,"height":1},"opacity":1,"edgeAntialiasingMask":251658240,"height":85,"hidden":false,"anchorPoint":{"pointX":0.5,"pointY":0.5}},"objectID":"3BA243F5-BC1B-483F-BCEF-51EEA0382C90","layers":[{"animations":[],"layers":[],"texturedRectangle":{"singleTextureOpacity":1,"textXHeight":0.18823529411764706,"textBaseline":0.89069816925946399,"isBackgroundTexture":true,"isVerticalText":false,"textColor":[0.38823530077934265,0.71764713525772095,0.35686266422271729,1],"textureType":6},"initialState":{"affineTransform":[1,0,0,1,0,0],"masksToBounds":false,"rotation":0,"scale":1,"position":{"pointX":388.86000061035156,"pointY":49.359405517578125},"width":771,"sublayerTransform":[1,0,0,0,0,1,0,0,0,0,1,0,0,0,0,1],"contentsRect":{"y":0,"x":0,"width":1,"height":1},"opacity":1,"edgeAntialiasingMask":0,"height":85,"hidden":true,"anchorPoint":{"pointX":0.5,"pointY":0.5}},"texture":"F33182DAF0802F86363CC427156904DD"}]}]},{"animations":[],"initialState":{"affineTransform":[1,0,0,1,0,0],"masksToBounds":false,"rotation":0,"scale":1,"position":{"pointX":480,"pointY":270},"width":960,"sublayerTransform":[1,0,0,0,0,1,0,0,0,0,1,0,0,0,0,1],"contentsRect":{"y":0,"x":0,"width":1,"height":1},"opacity":1,"edgeAntialiasingMask":251658240,"height":540,"hidden":false,"anchorPoint":{"pointX":0.5,"pointY":0.5}},"layers":[{"animations":[],"initialState":{"affineTransform":[1,0,0,1,0,0],"masksToBounds":false,"rotation":0,"scale":1,"position":{"pointX":478.63999938964844,"pointY":474.83148193359375},"width":796,"sublayerTransform":[1,0,0,0,0,1,0,0,0,0,1,0,0,0,0,1],"contentsRect":{"y":0,"x":0,"width":1,"height":1},"opacity":1,"edgeAntialiasingMask":251658240,"height":86,"hidden":false,"anchorPoint":{"pointX":0.5,"pointY":0.5}},"objectID":"4736A9F3-A4C1-4517-BA7C-0DD3768AF5F8","layers":[{"animations":[],"layers":[],"texturedRectangle":{"singleTextureOpacity":1,"textXHeight":0.18604651162790697,"textBaseline":0.88837478881658505,"isBackgroundTexture":true,"isVerticalText":false,"textColor":[0.38823530077934265,0.71764713525772095,0.35686266422271729,1],"textureType":6},"initialState":{"affineTransform":[1,0,0,1,0,0],"masksToBounds":false,"rotation":0,"scale":1,"position":{"pointX":401.36000061035156,"pointY":49.16851806640625},"width":796,"sublayerTransform":[1,0,0,0,0,1,0,0,0,0,1,0,0,0,0,1],"contentsRect":{"y":0,"x":0,"width":1,"height":1},"opacity":1,"edgeAntialiasingMask":0,"height":86,"hidden":true,"anchorPoint":{"pointX":0.5,"pointY":0.5}},"texture":"C464F2D59028BE3F1FC009DADE559130"}]}]},{"animations":[],"initialState":{"affineTransform":[1,0,0,1,0,0],"masksToBounds":false,"rotation":0,"scale":1,"position":{"pointX":480,"pointY":270},"width":960,"sublayerTransform":[1,0,0,0,0,1,0,0,0,0,1,0,0,0,0,1],"contentsRect":{"y":0,"x":0,"width":1,"height":1},"opacity":1,"edgeAntialiasingMask":251658240,"height":540,"hidden":false,"anchorPoint":{"pointX":0.5,"pointY":0.5}},"layers":[{"animations":[],"initialState":{"affineTransform":[1,0,0,1,0,0],"masksToBounds":false,"rotation":0,"scale":1,"position":{"pointX":332.64000701904297,"pointY":66.080001831054688},"width":504,"sublayerTransform":[1,0,0,0,0,1,0,0,0,0,1,0,0,0,0,1],"contentsRect":{"y":0,"x":0,"width":1,"height":1},"opacity":1,"edgeAntialiasingMask":251658240,"height":40,"hidden":false,"anchorPoint":{"pointX":0.5,"pointY":0.5}},"layers":[{"animations":[],"layers":[],"texturedRectangle":{"singleTextureOpacity":1,"textXHeight":0.56689453125,"textBaseline":0.90257133245468135,"isBackgroundTexture":true,"isVerticalText":false,"textColor":[0,0,0,1],"textureType":6},"initialState":{"affineTransform":[1,0,0,1,0,0],"masksToBounds":false,"rotation":0,"scale":1,"position":{"pointX":255.35999298095703,"pointY":59.919998168945312},"width":504,"sublayerTransform":[1,0,0,0,0,1,0,0,0,0,1,0,0,0,0,1],"contentsRect":{"y":0,"x":0,"width":1,"height":1},"opacity":1,"edgeAntialiasingMask":0,"height":40,"hidden":false,"anchorPoint":{"pointX":0.5,"pointY":0.5}},"texture":"2E9FB1162F3DF28E3881A13DDAE96203"}]}]}]}},{"effects":[{"beginTime":0,"baseLayer":{"animations":[],"initialState":{"affineTransform":[1,0,0,1,0,0],"masksToBounds":false,"rotation":0,"scale":1,"position":{"pointX":478.63999938964844,"pointY":474.83148193359375},"width":796,"sublayerTransform":[1,0,0,0,0,1,0,0,0,0,1,0,0,0,0,1],"contentsRect":{"y":0,"x":0,"width":1,"height":1},"opacity":1,"edgeAntialiasingMask":251658240,"height":86,"hidden":false,"anchorPoint":{"pointX":0.5,"pointY":0.5}},"objectID":"4736A9F3-A4C1-4517-BA7C-0DD3768AF5F8","layers":[{"animations":[],"initialState":{"affineTransform":[1,0,0,1,0,0],"masksToBounds":false,"rotation":0,"scale":1,"position":{"pointX":399.36000061035156,"pointY":-161.83148193359375},"width":796,"sublayerTransform":[1,0,0,0,0,1,0,0,0,0,1,-0.00070015824933551967,0,0,0,1],"contentsRect":{"y":0,"x":0,"width":1,"height":1},"opacity":1,"edgeAntialiasingMask":251658240,"height":86,"hidden":false,"anchorPoint":{"pointX":0.50170854348034111,"pointY":-1.8817614178324855}},"layers":[{"animations":[{"timeOffset":0,"beginTime":1e-100,"repeatCount":0,"animations":[{"timeOffset":0,"from":{"scalar":0},"beginTime":0,"repeatCount":0,"fillMode":"both","duration":1,"autoreverses":false,"timingFunction":"EaseInEaseOut","property":"opacity","to":{"scalar":1}},{"timeOffset":0,"from":{"scalar":false},"beginTime":0,"repeatCount":0,"fillMode":"forwards","property":"hidden","autoreverses":false,"duration":1,"to":{"scalar":false}}],"fillMode":"both","autoreverses":false,"duration":1}],"layers":[],"texturedRectangle":{"singleTextureOpacity":1,"textXHeight":0.18604651162790697,"textBaseline":0.88837478881658505,"isBackgroundTexture":true,"isVerticalText":false,"textColor":[0.38823530077934265,0.71764713525772095,0.35686266422271729,1],"textureType":6},"initialState":{"affineTransform":[1,0,0,1,0,0],"masksToBounds":false,"rotation":0,"scale":1,"position":{"pointX":401.36000061035156,"pointY":49.16851806640625},"width":796,"sublayerTransform":[1,0,0,0,0,1,0,0,0,0,1,0,0,0,0,1],"contentsRect":{"y":0,"x":0,"width":1,"height":1},"opacity":1,"edgeAntialiasingMask":0,"height":86,"hidden":true,"anchorPoint":{"pointX":0.5,"pointY":0.5}},"texture":"C464F2D59028BE3F1FC009DADE559130"}]}]},"effects":[],"duration":1,"type":"buildIn","name":"apple:dissolve character","objectID":"4736A9F3-A4C1-4517-BA7C-0DD3768AF5F8"}],"automaticPlay":false,"hyperlinks":[],"accessibility":[{"text":"Javascript operations","targetRectangle":{"y":75.680001735687256,"x":84.240006923675537,"width":500.88867140561342,"height":59}},{"text":"All outside operations (Database connections, WebSite requests, etc) needs to be synchronised with callbacks","targetRectangle":{"y":235.28991079330444,"x":120.23999929428101,"width":757.1875,"height":86}},{"text":"The order that your code was written sometimes is different that will be executed","targetRectangle":{"y":142.76018667221069,"x":120.23999929428101,"width":701.6875,"height":86}},{"text":"#SFNODE","targetRectangle":{"y":506.03670644760132,"x":812.03787851333618,"width":135.94970703125,"height":30}},{"text":"Challenge 1: How to reuse and pass ahead results to dependent functions","targetRectangle":{"y":338.74059438705444,"x":120.23999929428101,"width":741.921875,"height":87}}],"baseLayer":{"animations":[],"initialState":{"affineTransform":[1,0,0,1,0,0],"masksToBounds":false,"rotation":0,"scale":1,"position":{"pointX":480,"pointY":270},"width":960,"sublayerTransform":[1,0,0,0,0,1,0,0,0,0,1,0,0,0,0,1],"contentsRect":{"y":0,"x":0,"width":1,"height":1},"opacity":1,"edgeAntialiasingMask":251658240,"height":540,"hidden":false,"anchorPoint":{"pointX":0.5,"pointY":0.5}},"layers":[{"animations":[],"initialState":{"affineTransform":[1,0,0,1,0,0],"masksToBounds":false,"rotation":0,"scale":1,"position":{"pointX":480,"pointY":270},"width":960,"sublayerTransform":[1,0,0,0,0,1,0,0,0,0,1,0,0,0,0,1],"contentsRect":{"y":0,"x":0,"width":1,"height":1},"opacity":1,"edgeAntialiasingMask":251658240,"height":540,"hidden":false,"anchorPoint":{"pointX":0.5,"pointY":0.5}},"layers":[{"animations":[],"initialState":{"affineTransform":[1,0,0,1,0,0],"masksToBounds":false,"rotation":0,"scale":1,"position":{"pointX":480,"pointY":270},"width":960,"sublayerTransform":[1,0,0,0,0,1,0,0,0,0,1,0,0,0,0,1],"contentsRect":{"y":0,"x":0,"width":1,"height":1},"opacity":1,"edgeAntialiasingMask":251658240,"height":540,"hidden":false,"anchorPoint":{"pointX":0.5,"pointY":0.5}},"layers":[{"animations":[],"layers":[],"texturedRectangle":{"isBackgroundTexture":true,"singleTextureOpacity":1,"textureType":1,"textBaseline":0,"textXHeight":0,"isVerticalText":false},"initialState":{"affineTransform":[1,0,0,1,0,0],"masksToBounds":false,"rotation":0,"scale":1,"position":{"pointX":480,"pointY":270},"width":960,"sublayerTransform":[1,0,0,0,0,1,0,0,0,0,1,0,0,0,0,1],"contentsRect":{"y":0,"x":0,"width":1,"height":1},"opacity":1,"edgeAntialiasingMask":0,"height":540,"hidden":false,"anchorPoint":{"pointX":0.5,"pointY":0.5}},"texture":"079F8AD6B4545016392B41106591B174"}]}]},{"animations":[],"initialState":{"affineTransform":[1,0,0,1,0,0],"masksToBounds":false,"rotation":0,"scale":1,"position":{"pointX":480,"pointY":270},"width":960,"sublayerTransform":[1,0,0,0,0,1,0,0,0,0,1,0,0,0,0,1],"contentsRect":{"y":0,"x":0,"width":1,"height":1},"opacity":1,"edgeAntialiasingMask":251658240,"height":540,"hidden":false,"anchorPoint":{"pointX":0.5,"pointY":0.5}},"layers":[{"animations":[],"initialState":{"affineTransform":[1,0,0,1,0,0],"masksToBounds":false,"rotation":0,"scale":1,"position":{"pointX":446.13999938964844,"pointY":178.16018676757812},"width":731,"sublayerTransform":[1,0,0,0,0,1,0,0,0,0,1,0,0,0,0,1],"contentsRect":{"y":0,"x":0,"width":1,"height":1},"opacity":1,"edgeAntialiasingMask":251658240,"height":78,"hidden":false,"anchorPoint":{"pointX":0.5,"pointY":0.5}},"objectID":"E7B7560B-CD61-4C89-AFD2-CEED0062D82E","layers":[{"animations":[],"layers":[],"texturedRectangle":{"singleTextureOpacity":1,"textXHeight":0.20512820512820512,"textBaseline":0.97088380348988068,"isBackgroundTexture":true,"isVerticalText":false,"textColor":[0.38823530077934265,0.71764713525772095,0.35686266422271729,1],"textureType":6},"initialState":{"affineTransform":[1,0,0,1,0,0],"masksToBounds":false,"rotation":0,"scale":1,"position":{"pointX":368.86000061035156,"pointY":44.839813232421875},"width":731,"sublayerTransform":[1,0,0,0,0,1,0,0,0,0,1,0,0,0,0,1],"contentsRect":{"y":0,"x":0,"width":1,"height":1},"opacity":1,"edgeAntialiasingMask":0,"height":78,"hidden":false,"anchorPoint":{"pointX":0.5,"pointY":0.5}},"texture":"F443A070570E84E4A145F1050C9A95C9"}]}]},{"animations":[],"initialState":{"affineTransform":[1,0,0,1,0,0],"masksToBounds":false,"rotation":0,"scale":1,"position":{"pointX":480,"pointY":270},"width":960,"sublayerTransform":[1,0,0,0,0,1,0,0,0,0,1,0,0,0,0,1],"contentsRect":{"y":0,"x":0,"width":1,"height":1},"opacity":1,"edgeAntialiasingMask":251658240,"height":540,"hidden":false,"anchorPoint":{"pointX":0.5,"pointY":0.5}},"layers":[{"animations":[],"initialState":{"affineTransform":[1,0,0,1,0,0],"masksToBounds":false,"rotation":0,"scale":1,"position":{"pointX":720.80072021484375,"pointY":513.93670654296875},"width":137,"sublayerTransform":[1,0,0,0,0,1,0,0,0,0,1,0,0,0,0,1],"contentsRect":{"y":0,"x":0,"width":1,"height":1},"opacity":1,"edgeAntialiasingMask":251658240,"height":23,"hidden":false,"anchorPoint":{"pointX":0.5,"pointY":0.5}},"layers":[{"animations":[],"layers":[],"texturedRectangle":{"singleTextureOpacity":1,"textXHeight":0.59602156929347827,"textBaseline":0.9038123047870138,"isBackgroundTexture":true,"isVerticalText":false,"textColor":[0.38823530077934265,0.71764713525772095,0.35686266422271729,1],"textureType":6},"initialState":{"affineTransform":[1,0,0,1,0,0],"masksToBounds":false,"rotation":0,"scale":1,"position":{"pointX":228.19927978515625,"pointY":19.06329345703125},"width":137,"sublayerTransform":[1,0,0,0,0,1,0,0,0,0,1,0,0,0,0,1],"contentsRect":{"y":0,"x":0,"width":1,"height":1},"opacity":1,"edgeAntialiasingMask":0,"height":23,"hidden":false,"anchorPoint":{"pointX":0.5,"pointY":0.5}},"texture":"7AAC0F4B7584D4356B06C17CD57555BD"}]}]},{"animations":[],"initialState":{"affineTransform":[1,0,0,1,0,0],"masksToBounds":false,"rotation":0,"scale":1,"position":{"pointX":480,"pointY":270},"width":960,"sublayerTransform":[1,0,0,0,0,1,0,0,0,0,1,0,0,0,0,1],"contentsRect":{"y":0,"x":0,"width":1,"height":1},"opacity":1,"edgeAntialiasingMask":251658240,"height":540,"hidden":false,"anchorPoint":{"pointX":0.5,"pointY":0.5}},"layers":[{"animations":[],"initialState":{"affineTransform":[1,0,0,1,0,0],"masksToBounds":false,"rotation":0,"scale":1,"position":{"pointX":474.13999938964844,"pointY":274.18991088867188},"width":787,"sublayerTransform":[1,0,0,0,0,1,0,0,0,0,1,0,0,0,0,1],"contentsRect":{"y":0,"x":0,"width":1,"height":1},"opacity":1,"edgeAntialiasingMask":251658240,"height":85,"hidden":false,"anchorPoint":{"pointX":0.5,"pointY":0.5}},"objectID":"2B50C4D3-6360-41FA-8440-50B175239820","layers":[{"animations":[],"layers":[],"texturedRectangle":{"singleTextureOpacity":1,"textXHeight":0.18823529411764706,"textBaseline":0.88539600933299345,"isBackgroundTexture":true,"isVerticalText":false,"textColor":[0.38823530077934265,0.71764713525772095,0.35686266422271729,1],"textureType":6},"initialState":{"affineTransform":[1,0,0,1,0,0],"masksToBounds":false,"rotation":0,"scale":1,"position":{"pointX":396.86000061035156,"pointY":48.810089111328125},"width":787,"sublayerTransform":[1,0,0,0,0,1,0,0,0,0,1,0,0,0,0,1],"contentsRect":{"y":0,"x":0,"width":1,"height":1},"opacity":1,"edgeAntialiasingMask":0,"height":85,"hidden":false,"anchorPoint":{"pointX":0.5,"pointY":0.5}},"texture":"D94CCB6C708FE641EC745EEE0EC46C84"}]}]},{"animations":[],"initialState":{"affineTransform":[1,0,0,1,0,0],"masksToBounds":false,"rotation":0,"scale":1,"position":{"pointX":480,"pointY":270},"width":960,"sublayerTransform":[1,0,0,0,0,1,0,0,0,0,1,0,0,0,0,1],"contentsRect":{"y":0,"x":0,"width":1,"height":1},"opacity":1,"edgeAntialiasingMask":251658240,"height":540,"hidden":false,"anchorPoint":{"pointX":0.5,"pointY":0.5}},"layers":[{"animations":[],"initialState":{"affineTransform":[1,0,0,1,0,0],"masksToBounds":false,"rotation":0,"scale":1,"position":{"pointX":466.13999938964844,"pointY":377.64059448242188},"width":771,"sublayerTransform":[1,0,0,0,0,1,0,0,0,0,1,0,0,0,0,1],"contentsRect":{"y":0,"x":0,"width":1,"height":1},"opacity":1,"edgeAntialiasingMask":251658240,"height":85,"hidden":false,"anchorPoint":{"pointX":0.5,"pointY":0.5}},"objectID":"3BA243F5-BC1B-483F-BCEF-51EEA0382C90","layers":[{"animations":[],"layers":[],"texturedRectangle":{"singleTextureOpacity":1,"textXHeight":0.18823529411764706,"textBaseline":0.89069816925946399,"isBackgroundTexture":true,"isVerticalText":false,"textColor":[0.38823530077934265,0.71764713525772095,0.35686266422271729,1],"textureType":6},"initialState":{"affineTransform":[1,0,0,1,0,0],"masksToBounds":false,"rotation":0,"scale":1,"position":{"pointX":388.86000061035156,"pointY":49.359405517578125},"width":771,"sublayerTransform":[1,0,0,0,0,1,0,0,0,0,1,0,0,0,0,1],"contentsRect":{"y":0,"x":0,"width":1,"height":1},"opacity":1,"edgeAntialiasingMask":0,"height":85,"hidden":false,"anchorPoint":{"pointX":0.5,"pointY":0.5}},"texture":"F33182DAF0802F86363CC427156904DD"}]}]},{"animations":[],"initialState":{"affineTransform":[1,0,0,1,0,0],"masksToBounds":false,"rotation":0,"scale":1,"position":{"pointX":480,"pointY":270},"width":960,"sublayerTransform":[1,0,0,0,0,1,0,0,0,0,1,0,0,0,0,1],"contentsRect":{"y":0,"x":0,"width":1,"height":1},"opacity":1,"edgeAntialiasingMask":251658240,"height":540,"hidden":false,"anchorPoint":{"pointX":0.5,"pointY":0.5}},"layers":[{"animations":[],"initialState":{"affineTransform":[1,0,0,1,0,0],"masksToBounds":false,"rotation":0,"scale":1,"position":{"pointX":478.63999938964844,"pointY":474.83148193359375},"width":796,"sublayerTransform":[1,0,0,0,0,1,0,0,0,0,1,0,0,0,0,1],"contentsRect":{"y":0,"x":0,"width":1,"height":1},"opacity":1,"edgeAntialiasingMask":251658240,"height":86,"hidden":false,"anchorPoint":{"pointX":0.5,"pointY":0.5}},"objectID":"4736A9F3-A4C1-4517-BA7C-0DD3768AF5F8","layers":[{"animations":[],"layers":[],"texturedRectangle":{"singleTextureOpacity":1,"textXHeight":0.18604651162790697,"textBaseline":0.88837478881658505,"isBackgroundTexture":true,"isVerticalText":false,"textColor":[0.38823530077934265,0.71764713525772095,0.35686266422271729,1],"textureType":6},"initialState":{"affineTransform":[1,0,0,1,0,0],"masksToBounds":false,"rotation":0,"scale":1,"position":{"pointX":401.36000061035156,"pointY":49.16851806640625},"width":796,"sublayerTransform":[1,0,0,0,0,1,0,0,0,0,1,0,0,0,0,1],"contentsRect":{"y":0,"x":0,"width":1,"height":1},"opacity":1,"edgeAntialiasingMask":0,"height":86,"hidden":true,"anchorPoint":{"pointX":0.5,"pointY":0.5}},"texture":"C464F2D59028BE3F1FC009DADE559130"}]}]},{"animations":[],"initialState":{"affineTransform":[1,0,0,1,0,0],"masksToBounds":false,"rotation":0,"scale":1,"position":{"pointX":480,"pointY":270},"width":960,"sublayerTransform":[1,0,0,0,0,1,0,0,0,0,1,0,0,0,0,1],"contentsRect":{"y":0,"x":0,"width":1,"height":1},"opacity":1,"edgeAntialiasingMask":251658240,"height":540,"hidden":false,"anchorPoint":{"pointX":0.5,"pointY":0.5}},"layers":[{"animations":[],"initialState":{"affineTransform":[1,0,0,1,0,0],"masksToBounds":false,"rotation":0,"scale":1,"position":{"pointX":332.64000701904297,"pointY":66.080001831054688},"width":504,"sublayerTransform":[1,0,0,0,0,1,0,0,0,0,1,0,0,0,0,1],"contentsRect":{"y":0,"x":0,"width":1,"height":1},"opacity":1,"edgeAntialiasingMask":251658240,"height":40,"hidden":false,"anchorPoint":{"pointX":0.5,"pointY":0.5}},"layers":[{"animations":[],"layers":[],"texturedRectangle":{"singleTextureOpacity":1,"textXHeight":0.56689453125,"textBaseline":0.90257133245468135,"isBackgroundTexture":true,"isVerticalText":false,"textColor":[0,0,0,1],"textureType":6},"initialState":{"affineTransform":[1,0,0,1,0,0],"masksToBounds":false,"rotation":0,"scale":1,"position":{"pointX":255.35999298095703,"pointY":59.919998168945312},"width":504,"sublayerTransform":[1,0,0,0,0,1,0,0,0,0,1,0,0,0,0,1],"contentsRect":{"y":0,"x":0,"width":1,"height":1},"opacity":1,"edgeAntialiasingMask":0,"height":40,"hidden":false,"anchorPoint":{"pointX":0.5,"pointY":0.5}},"texture":"2E9FB1162F3DF28E3881A13DDAE96203"}]}]}]}},{"effects":[{"beginTime":0,"baseLayer":{"animations":[],"initialState":{"affineTransform":[1,0,0,1,0,0],"masksToBounds":false,"rotation":0,"scale":1,"position":{"pointX":480,"pointY":270},"width":960,"sublayerTransform":[1,0,0,0,0,1,0,0,0,0,1,0,0,0,0,1],"contentsRect":{"y":0,"x":0,"width":1,"height":1},"opacity":1,"edgeAntialiasingMask":251658240,"height":540,"hidden":false,"anchorPoint":{"pointX":0.5,"pointY":0.5}},"objectID":"0","layers":[{"animations":[],"initialState":{"affineTransform":[1,0,0,1,0,0],"masksToBounds":false,"rotation":0,"scale":1,"position":{"pointX":480,"pointY":270},"width":960,"sublayerTransform":[1,0,0,0,0,1,0,0,0,0,1,-0.00070015824933551967,0,0,0,1],"contentsRect":{"y":0,"x":0,"width":1,"height":1},"opacity":1,"edgeAntialiasingMask":251658240,"height":540,"hidden":false,"anchorPoint":{"pointX":0.5,"pointY":0.5}},"layers":[{"animations":[],"layers":[],"texturedRectangle":{"isBackgroundTexture":false,"singleTextureOpacity":1,"textureType":0,"textBaseline":0,"textXHeight":0,"isVerticalText":false},"initialState":{"affineTransform":[1,0,0,1,0,0],"masksToBounds":false,"rotation":0,"scale":1,"position":{"pointX":480,"pointY":270},"width":960,"sublayerTransform":[1,0,0,0,0,1,0,0,0,0,1,0,0,0,0,1],"contentsRect":{"y":0,"x":0,"width":1,"height":1},"opacity":1,"edgeAntialiasingMask":0,"height":540,"hidden":false,"anchorPoint":{"pointX":0.5,"pointY":0.5}},"texture":"5F50A526B1A711C07C54BC979DB6105C"},{"animations":[{"timeOffset":0,"from":{"scalar":false},"beginTime":0,"repeatCount":0,"fillMode":"both","property":"hidden","autoreverses":false,"duration":0.01,"to":{"scalar":true}}],"layers":[],"texturedRectangle":{"isBackgroundTexture":false,"singleTextureOpacity":1,"textureType":0,"textBaseline":0,"textXHeight":0,"isVerticalText":false},"initialState":{"affineTransform":[1,0,0,1,0,0],"masksToBounds":false,"rotation":0,"scale":1,"position":{"pointX":480,"pointY":270},"width":960,"sublayerTransform":[1,0,0,0,0,1,0,0,0,0,1,0,0,0,0,1],"contentsRect":{"y":0,"x":0,"width":1,"height":1},"opacity":1,"edgeAntialiasingMask":0,"height":540,"hidden":false,"anchorPoint":{"pointX":0.5,"pointY":0.5}},"texture":"3F92E9D33FC6814A8ECAE3254A8DC26C"}]}]},"effects":[],"duration":0.01,"type":"transition","name":"none","objectID":"0"}],"automaticPlay":false,"hyperlinks":[],"accessibility":[{"text":"Javascript operations","targetRectangle":{"y":75.680001735687256,"x":84.240006923675537,"width":500.88867140561342,"height":59}},{"text":"All outside operations (Database connections, WebSite requests, etc) needs to be synchronised with callbacks","targetRectangle":{"y":235.28991079330444,"x":120.23999929428101,"width":757.1875,"height":86}},{"text":"Challenge 2: How to manage exception errors of each single function","targetRectangle":{"y":435.43148183822632,"x":120.23999929428101,"width":766.5,"height":87}},{"text":"The order that your code was written sometimes is different that will be executed","targetRectangle":{"y":142.76018667221069,"x":120.23999929428101,"width":701.6875,"height":86}},{"text":"#SFNODE","targetRectangle":{"y":506.03670644760132,"x":812.03787851333618,"width":135.94970703125,"height":30}},{"text":"Challenge 1: How to reuse and pass ahead results to dependent functions","targetRectangle":{"y":338.74059438705444,"x":120.23999929428101,"width":741.921875,"height":87}}],"baseLayer":{"animations":[],"initialState":{"affineTransform":[1,0,0,1,0,0],"masksToBounds":false,"rotation":0,"scale":1,"position":{"pointX":480,"pointY":270},"width":960,"sublayerTransform":[1,0,0,0,0,1,0,0,0,0,1,0,0,0,0,1],"contentsRect":{"y":0,"x":0,"width":1,"height":1},"opacity":1,"edgeAntialiasingMask":251658240,"height":540,"hidden":false,"anchorPoint":{"pointX":0.5,"pointY":0.5}},"objectID":"0","layers":[{"animations":[],"initialState":{"affineTransform":[1,0,0,1,0,0],"masksToBounds":false,"rotation":0,"scale":1,"position":{"pointX":480,"pointY":270},"width":960,"sublayerTransform":[1,0,0,0,0,1,0,0,0,0,1,-0.00070015824933551967,0,0,0,1],"contentsRect":{"y":0,"x":0,"width":1,"height":1},"opacity":1,"edgeAntialiasingMask":251658240,"height":540,"hidden":false,"anchorPoint":{"pointX":0.5,"pointY":0.5}},"layers":[{"animations":[],"layers":[],"texturedRectangle":{"isBackgroundTexture":false,"singleTextureOpacity":1,"textureType":0,"textBaseline":0,"textXHeight":0,"isVerticalText":false},"initialState":{"affineTransform":[1,0,0,1,0,0],"masksToBounds":false,"rotation":0,"scale":1,"position":{"pointX":480,"pointY":270},"width":960,"sublayerTransform":[1,0,0,0,0,1,0,0,0,0,1,0,0,0,0,1],"contentsRect":{"y":0,"x":0,"width":1,"height":1},"opacity":1,"edgeAntialiasingMask":0,"height":540,"hidden":false,"anchorPoint":{"pointX":0.5,"pointY":0.5}},"texture":"3F92E9D33FC6814A8ECAE3254A8DC26C"}]}]}}]}